{"date":"Monday, June 15, 2026","generated":"2026-06-15T13:41:23.521Z","batch":77,"picks":[{"sym":"HRI","name":"Herc Holdings","sector":"Industrials","price":149.36,"change":4.74,"pct":3.2776,"pe":4829.3027,"beta":1.8652129,"analystBuy":0,"analystSell":0,"rating":"WATCH","confidence":85,"reason":"Extreme PE ratio of 4829x indicates minimal/no earnings. Unsustainable valuation.","target":120.45,"technicalSignal":"Bearish","fundamentalScore":"Weak","macroAlignment":"Unfavorable","date":"2026-06-15","priceAtPick":149.36,"timestamp":1781530880296},{"sym":"URI","name":"United Rentals","sector":"Industrials","price":1078.54,"change":4.3,"pct":0.4003,"pe":26.9837,"beta":1.7984282,"analystBuy":0,"analystSell":0,"rating":"BUY","confidence":72,"reason":"Strong historical returns, high beta offers growth potential with equipment demand","target":1185.32,"technicalSignal":"Bullish","fundamentalScore":"Strong","macroAlignment":"Favorable","date":"2026-06-15","priceAtPick":1078.54,"timestamp":1781530881332},{"sym":"GWW","name":"W.W. Grainger","sector":"Industrials","price":1311.61,"change":-4.26,"pct":-0.3237,"pe":36.4164,"beta":1.0415133,"analystBuy":0,"analystSell":0,"rating":"WATCH","confidence":58,"reason":"High valuation at 36.4x PE; cyclical industrials vulnerable to economic slowdown","target":1345,"technicalSignal":"Neutral","fundamentalScore":"Mixed","macroAlignment":"Uncertain","date":"2026-06-15","priceAtPick":1311.61,"timestamp":1781530882507},{"sym":"MSM","name":"MSC Industrial","sector":"Industrials","price":117.87,"change":1.18,"pct":1.0112,"pe":32.6864,"beta":0.822974,"analystBuy":0,"analystSell":0,"rating":"WATCH","confidence":62,"reason":"High PE 32.7x limits upside; low beta suggests stability","target":120.5,"technicalSignal":"Neutral","fundamentalScore":"Moderate","macroAlignment":"Neutral","date":"2026-06-15","priceAtPick":117.87,"timestamp":1781530883521}],"macro":{"spyPct":"1.52","qqqPct":"2.55","vix":"0.0","tltPct":"0.28","riskOn":false}}