{"date":"Tuesday, June 30, 2026","generated":"2026-06-30T13:17:47.966Z","batch":5,"picks":[{"sym":"KO","name":"Coca-Cola","sector":"Consumer Staples","price":82.65,"change":0.02,"pct":0.0242,"pe":27.3275,"beta":0.34462214,"analystBuy":0,"analystSell":0,"rating":"AVOID","confidence":76,"reason":"Underperforming market -1.6% in risk-off environment; PE 27.3x expensive for 5.1% growth","target":79.5,"technicalSignal":"Bearish","fundamentalScore":"Moderate","macroAlignment":"Unfavorable","date":"2026-06-30","priceAtPick":82.65,"timestamp":1782825461456},{"sym":"PEP","name":"PepsiCo","sector":"Consumer Staples","price":138.68,"change":-2.71,"pct":-1.9167,"pe":23.4524,"beta":0.3672644,"analystBuy":0,"analystSell":0,"rating":"AVOID","confidence":76,"reason":"Underperforming market -3.6% in risk-off environment; elevated PE 23.5x vs 4.3% growth","target":132.5,"technicalSignal":"Bearish","fundamentalScore":"Weak","macroAlignment":"Unfavorable","date":"2026-06-30","priceAtPick":138.68,"timestamp":1782825463578},{"sym":"TMO","name":"Thermo Fisher","sector":"Health Care","price":506.42,"change":-6.61,"pct":-1.2884,"pe":27.8663,"beta":0.8577226,"analystBuy":0,"analystSell":0,"rating":"AVOID","confidence":76,"reason":"Underperforming market -2.9% in mixed rally; Health Care rotating out; PE 27.9x unjustified by 5.4% growth","target":485,"technicalSignal":"Bearish","fundamentalScore":"Weak","macroAlignment":"Unfavorable","date":"2026-06-30","priceAtPick":506.42,"timestamp":1782825465140},{"sym":"ORCL","name":"Oracle","sector":"Technology","price":147.76,"change":-0.77,"pct":-0.5184,"pe":25.8799,"beta":1.7216094,"analystBuy":0,"analystSell":0,"rating":"WATCH","confidence":62,"reason":"High beta (1.72) amplifies risk-off dollar strength; AI catalyst offset by underperformance","target":145.5,"technicalSignal":"Bearish","fundamentalScore":"Mixed","macroAlignment":"Unfavorable","date":"2026-06-30","priceAtPick":147.76,"timestamp":1782825466754},{"sym":"AMD","name":"AMD","sector":"Technology","price":539.49,"change":17.91,"pct":3.4338,"pe":202.0139,"beta":2.5111241,"analystBuy":0,"analystSell":0,"rating":"BUY","confidence":76,"reason":"AI momentum breakout, outperforming +1.8%, strong revenue growth 35%, sector rotation in","target":566.46,"technicalSignal":"Bullish","fundamentalScore":"Mixed","macroAlignment":"Favorable","date":"2026-06-30","priceAtPick":539.49,"timestamp":1782825467966}],"macro":{"spyPct":"1.65","qqqPct":"2.49","vix":"0.0","tltPct":"0.10","riskOn":false}}