{"date":"Wednesday, June 24, 2026","generated":"2026-06-24T13:55:58.308Z","batch":15,"picks":[{"sym":"MELI","name":"MercadoLibre","sector":"Consumer Discretionary","price":1626.28,"change":42.62,"pct":2.6912,"pe":40.3652,"beta":1.3809808,"analystBuy":0,"analystSell":0,"rating":"BUY","confidence":76,"reason":"Strong revenue growth 42.1%, outperforming market +2.2%, momentum positive despite sector headwinds","target":1707.59,"technicalSignal":"Bullish","fundamentalScore":"Strong","macroAlignment":"Favorable","date":"2026-06-24","priceAtPick":1626.28,"timestamp":1782309352922},{"sym":"REGN","name":"Regeneron","sector":"Health Care","price":625.13,"change":7.1,"pct":1.1488,"pe":14.2912,"beta":0.23522867,"analystBuy":0,"analystSell":0,"rating":"BUY","confidence":76,"reason":"FDA/EMA approval catalyst, strong fundamentals (14.3x PE, 85.7% margin), sector rotation tailwind","target":656.39,"technicalSignal":"Bullish","fundamentalScore":"Strong","macroAlignment":"Favorable","date":"2026-06-24","priceAtPick":625.13,"timestamp":1782309354941},{"sym":"GILD","name":"Gilead Sciences","sector":"Health Care","price":126.12,"change":1.07,"pct":0.8557,"pe":18.3688,"beta":0.3636174,"analystBuy":0,"analystSell":0,"rating":"BUY","confidence":76,"reason":"Trodelvy approval catalyst, defensive beta, sector rotation into healthcare","target":134.28,"technicalSignal":"Bullish","fundamentalScore":"Strong","macroAlignment":"Favorable","date":"2026-06-24","priceAtPick":126.12,"timestamp":1782309355990},{"sym":"ZTS","name":"Zoetis","sector":"Health Care","price":78.77,"change":1.93,"pct":2.5117,"pe":12.0514,"beta":0.72447175,"analystBuy":0,"analystSell":0,"rating":"BUY","confidence":76,"reason":"Outperforming +2.0%, low beta defensive play, sector rotation catalyst","target":81.5,"technicalSignal":"Bullish","fundamentalScore":"Strong","macroAlignment":"Favorable","date":"2026-06-24","priceAtPick":78.77,"timestamp":1782309357129},{"sym":"AON","name":"Aon","sector":"Financials","price":321.26,"change":0.52,"pct":0.1621,"pe":18.6514,"beta":0.7007035,"analystBuy":0,"analystSell":0,"rating":"WATCH","confidence":62,"reason":"Defensive positioning (beta 0.7) conflicts with risk-off environment; no analyst coverage creates uncertainty","target":328.5,"technicalSignal":"Neutral","fundamentalScore":"Solid","macroAlignment":"Mixed","date":"2026-06-24","priceAtPick":321.26,"timestamp":1782309358307}],"macro":{"spyPct":"0.51","qqqPct":"0.47","vix":"0.0","tltPct":"1.23","riskOn":false}}