{"date":"Thursday, June 18, 2026","generated":"2026-06-18T14:11:59.289Z","batch":93,"picks":[{"sym":"TIGR","name":"UP Fintech","sector":"Financials","price":4.72,"change":0.01,"pct":0.2123,"pe":5.2002,"beta":0.5039896,"analystBuy":0,"analystSell":0,"rating":"WATCH","confidence":55,"reason":"Attractive valuation and growth offset by no analyst coverage, rising short interest, and risk-off environment.","target":4.95,"technicalSignal":"Neutral","fundamentalScore":"Strong","macroAlignment":"Unfavorable","date":"2026-06-18","priceAtPick":4.72,"timestamp":1781791914351},{"sym":"MPNGY","name":"Mpanga","sector":"Financials","price":18.88,"change":-0.28,"pct":-1.4614,"pe":null,"beta":1.1871101,"analystBuy":0,"analystSell":0,"rating":"AVOID","confidence":72,"reason":"Underperforming market -2.1%, no analyst coverage, weak margins despite high revenue growth","target":18.5,"technicalSignal":"Bearish","fundamentalScore":"Weak","macroAlignment":"Unfavorable","date":"2026-06-18","priceAtPick":18.88,"timestamp":1781791915580},{"sym":"NU","name":"Nu Holdings","sector":"Financials","price":12.93,"change":0.04,"pct":0.3103,"pe":21.8388,"beta":0.95180506,"analystBuy":0,"analystSell":0,"rating":"WATCH","confidence":55,"reason":"Citigroup downgrade conflicts with strong fundamentals; whale alerts warrant monitoring","target":13.25,"technicalSignal":"Neutral","fundamentalScore":"Strong","macroAlignment":"Neutral","date":"2026-06-18","priceAtPick":12.93,"timestamp":1781791916834},{"sym":"PAGS","name":"PagSeguro","sector":"Financials","price":8.96,"change":0.05,"pct":0.5612,"pe":5.9336,"beta":1.3039848,"analystBuy":0,"analystSell":0,"rating":"WATCH","confidence":58,"reason":"Valuation attractive (5.9x PE) but no analyst coverage, weak growth, risk-off environment headwinds","target":9.25,"technicalSignal":"Neutral","fundamentalScore":"Mixed","macroAlignment":"Unfavorable","date":"2026-06-18","priceAtPick":8.96,"timestamp":1781791918045},{"sym":"STNE","name":"StoneCo","sector":"Financials","price":10.93,"change":0.16,"pct":1.4856,"pe":5.779,"beta":1.6206365,"analystBuy":0,"analystSell":0,"rating":"WATCH","confidence":60,"reason":"Attractive valuation (5.8x PE) offset by high beta risk and no analyst coverage.","target":11.48,"technicalSignal":"Neutral","fundamentalScore":"Mixed","macroAlignment":"Neutral","date":"2026-06-18","priceAtPick":10.93,"timestamp":1781791919288}],"macro":{"spyPct":"0.59","qqqPct":"1.88","vix":"0.0","tltPct":"0.81","riskOn":false}}