{"date":"Thursday, June 25, 2026","generated":"2026-06-25T14:03:41.182Z","batch":86,"picks":[{"sym":"XLRE","name":"Real Estate ETF","sector":"Index","price":44.57,"change":0.06,"pct":0.1348,"beta":0.9807284,"analystBuy":0,"analystSell":0,"rating":"WATCH","confidence":58,"reason":"Mixed signals: housing data weak, but sector rotation catalysts present; flat momentum.","target":45.2,"technicalSignal":"Neutral","fundamentalScore":"Unclear","macroAlignment":"Mixed","date":"2026-06-25","priceAtPick":44.57,"timestamp":1782396215268},{"sym":"XLC","name":"Comm Services ETF","sector":"Index","price":106.21,"change":-0.33,"pct":-0.3097,"beta":0.98912424,"analystBuy":0,"analystSell":0,"rating":"WATCH","confidence":62,"reason":"Flat performance, no analyst coverage, sector rotation mixed signals unclear","target":106.8,"technicalSignal":"Neutral","fundamentalScore":"Insufficient Data","macroAlignment":"Neutral","date":"2026-06-25","priceAtPick":106.21,"timestamp":1782396216483},{"sym":"XLB","name":"Materials ETF","sector":"Index","price":51.84,"change":0.68,"pct":1.3292,"beta":0.9344721,"analystBuy":0,"analystSell":0,"rating":"WATCH","confidence":62,"reason":"Sector rotation out of materials; mixed macro signals with dollar strength offsetting equity gains","target":52.5,"technicalSignal":"Neutral","fundamentalScore":"Insufficient Data","macroAlignment":"Mixed","date":"2026-06-25","priceAtPick":51.84,"timestamp":1782396218803},{"sym":"IWM","name":"Russell 2000 ETF","sector":"Index","price":298.8,"change":2.11,"pct":0.7112,"beta":1.1180491,"analystBuy":0,"analystSell":0,"rating":"WATCH","confidence":62,"reason":"Small caps holding up amid breadth concerns; elevated shorts offset by dollar strength headwinds","target":305.2,"technicalSignal":"Neutral","fundamentalScore":"Incomplete","macroAlignment":"Mixed","date":"2026-06-25","priceAtPick":298.8,"timestamp":1782396219995},{"sym":"DIA","name":"Dow Jones ETF","sector":"Index","price":521.59,"change":3.07,"pct":0.5921,"beta":0.86439216,"analystBuy":0,"analystSell":0,"rating":"WATCH","confidence":58,"reason":"Market-neutral performance, risk-off environment conflicts with equity positioning","target":525.5,"technicalSignal":"Neutral","fundamentalScore":"Neutral","macroAlignment":"Mixed","date":"2026-06-25","priceAtPick":521.59,"timestamp":1782396221182}],"macro":{"spyPct":"-0.10","qqqPct":"-0.17","vix":"0.0","tltPct":"0.42","riskOn":false}}