{"date":"Wednesday, June 17, 2026","generated":"2026-06-17T13:27:52.267Z","batch":80,"picks":[{"sym":"W","name":"Wayfair","sector":"Consumer Discretionary","price":83.16,"change":0.17,"pct":0.2048,"pe":null,"beta":3.0275118,"analystBuy":0,"analystSell":0,"rating":"WATCH","confidence":45,"reason":"No PE ratio; high beta 3.03 indicates volatility risk","target":85.5,"technicalSignal":"Neutral","fundamentalScore":"Insufficient Data","macroAlignment":"Uncertain","date":"2026-06-17","priceAtPick":83.16,"timestamp":1781702866465},{"sym":"ETSY","name":"Etsy","sector":"Consumer Discretionary","price":73.34,"change":1.15,"pct":1.593,"pe":42.9409,"beta":1.8733017,"analystBuy":0,"analystSell":0,"rating":"WATCH","confidence":62,"reason":"High PE ratio and beta offset modest gains; monitor earnings","target":75.5,"technicalSignal":"Neutral","fundamentalScore":"Moderate","macroAlignment":"Mixed","date":"2026-06-17","priceAtPick":73.34,"timestamp":1781702867595},{"sym":"EBAY","name":"eBay","sector":"Consumer Discretionary","price":109.32,"change":0.14,"pct":0.1282,"pe":24.3358,"beta":1.3833413,"analystBuy":0,"analystSell":0,"rating":"WATCH","confidence":62,"reason":"eBay stable but valuation stretched; macro headwinds offset acquisition optimism","target":111.5,"technicalSignal":"Neutral","fundamentalScore":"Moderate","macroAlignment":"Mixed","date":"2026-06-17","priceAtPick":109.32,"timestamp":1781702868725},{"sym":"CHWY","name":"Chewy","sector":"Consumer Discretionary","price":18.87,"change":-0.47,"pct":-2.4302,"pe":34.6761,"beta":1.4291296,"analystBuy":0,"analystSell":0,"rating":"WATCH","confidence":58,"reason":"High PE valuation at 34.7x limits upside despite growth potential","target":20.45,"technicalSignal":"Neutral","fundamentalScore":"Mixed","macroAlignment":"Cautious","date":"2026-06-17","priceAtPick":18.87,"timestamp":1781702871151},{"sym":"PRTS","name":"CarParts.com","sector":"Consumer Discretionary","price":6.82,"change":0.26,"pct":3.9634,"pe":null,"beta":0.65690374,"analystBuy":0,"analystSell":0,"rating":"WATCH","confidence":45,"reason":"No PE ratio, limited liquidity signals, weak analyst coverage concern","target":7.05,"technicalSignal":"Neutral","fundamentalScore":"Weak","macroAlignment":"Neutral","date":"2026-06-17","priceAtPick":6.82,"timestamp":1781702872267}],"macro":{"spyPct":"-0.60","qqqPct":"-1.90","vix":"0.0","tltPct":"0.55","riskOn":false}}