{"date":"Monday, June 29, 2026","generated":"2026-06-29T13:51:49.689Z","batch":50,"picks":[{"sym":"AMT","name":"American Tower","sector":"Real Estate","price":174.42,"change":-1.17,"pct":-0.6663,"pe":32.3408,"beta":0.89859796,"analystBuy":0,"analystSell":0,"rating":"AVOID","confidence":76,"reason":"Underperforming market -2.0% in risk-off environment; high PE 32.3x lacks growth justification","target":168.5,"technicalSignal":"Bearish","fundamentalScore":"Weak","macroAlignment":"Unfavorable","date":"2026-06-29","priceAtPick":174.42,"timestamp":1782741103921},{"sym":"CCI","name":"Crown Castle","sector":"Real Estate","price":81.62,"change":-1,"pct":-1.2104,"pe":81.2155,"beta":0.9733475,"analystBuy":0,"analystSell":0,"rating":"AVOID","confidence":76,"reason":"Revenue collapse -29.6%, extreme PE 81.2x, underperforming market -2.6% in mixed environment","target":87.5,"technicalSignal":"Bearish","fundamentalScore":"Weak","macroAlignment":"Unfavorable","date":"2026-06-29","priceAtPick":81.62,"timestamp":1782741105202},{"sym":"EQIX","name":"Equinix","sector":"Real Estate","price":1099.31,"change":8.01,"pct":0.734,"pe":79.7249,"beta":0.9600365,"analystBuy":0,"analystSell":0,"rating":"AVOID","confidence":76,"reason":"Extreme PE 79.7x, lagging SPY despite market flatness, sector headwinds","target":1045,"technicalSignal":"Weak","fundamentalScore":"Deteriorating","macroAlignment":"Unfavorable","date":"2026-06-29","priceAtPick":1099.31,"timestamp":1782741106843},{"sym":"PSA","name":"Public Storage","sector":"Real Estate","price":321.61,"change":-2.78,"pct":-0.857,"pe":31.9199,"beta":0.9221308,"analystBuy":0,"analystSell":0,"rating":"AVOID","confidence":76,"reason":"Underperforming market by -2.2% in mixed environment; expensive valuation (PE 31.9x) vs weak 2.9% growth","target":305,"technicalSignal":"Bearish","fundamentalScore":"Weak","macroAlignment":"Unfavorable","date":"2026-06-29","priceAtPick":321.61,"timestamp":1782741108494},{"sym":"EXR","name":"Extra Space Storage","sector":"Real Estate","price":147.93,"change":-1.28,"pct":-0.8579,"pe":32.3637,"beta":1.171052,"analystBuy":0,"analystSell":0,"rating":"AVOID","confidence":76,"reason":"Earnings collapse, -2.2% underperformance, PE 32.4x overvalued vs 4.2% growth","target":138.5,"technicalSignal":"Bearish","fundamentalScore":"Weak","macroAlignment":"Unfavorable","date":"2026-06-29","priceAtPick":147.93,"timestamp":1782741109688}],"macro":{"spyPct":"1.38","qqqPct":"1.60","vix":"0.0","tltPct":"0.07","riskOn":false}}