{"date":"Friday, June 12, 2026","generated":"2026-06-12T13:32:57.628Z","batch":75,"picks":[{"sym":"WM","name":"Waste Management","sector":"Industrials","price":218.05,"change":-0.74,"pct":-0.3382,"pe":33.259,"beta":0.4428877,"analystBuy":0,"analystSell":0,"rating":"WATCH","confidence":62,"reason":"High PE ratio 33.3x offset by defensive characteristics and stability","target":225.5,"technicalSignal":"Neutral","fundamentalScore":"Fair","macroAlignment":"Favorable","date":"2026-06-12","priceAtPick":218.05,"timestamp":1781271174296},{"sym":"CWST","name":"Casella Waste","sector":"Industrials","price":90.92,"change":1.16,"pct":1.2923,"pe":731.9444,"beta":0.7433377,"analystBuy":0,"analystSell":0,"rating":"WATCH","confidence":45,"reason":"Extremely high PE ratio of 731.9x raises valuation concerns","target":92.5,"technicalSignal":"Neutral","fundamentalScore":"Weak","macroAlignment":"Neutral","date":"2026-06-12","priceAtPick":90.92,"timestamp":1781271175379},{"sym":"CLH","name":"Clean Harbors","sector":"Industrials","price":287.93,"change":1.15,"pct":0.401,"pe":39.0661,"beta":0.8703216,"analystBuy":0,"analystSell":0,"rating":"WATCH","confidence":62,"reason":"High PE ratio limits upside; stable beta suggests low volatility expectations","target":295.5,"technicalSignal":"Neutral","fundamentalScore":"Moderate","macroAlignment":"Neutral","date":"2026-06-12","priceAtPick":287.93,"timestamp":1781271176462},{"sym":"CECO","name":"CECO Environmental","sector":"Industrials","price":97.35,"change":0.94,"pct":0.975,"pe":113.4665,"beta":1.4474859,"analystBuy":0,"analystSell":0,"rating":"WATCH","confidence":45,"reason":"Extremely high PE ratio 113.5x raises valuation concerns despite positive momentum","target":99.5,"technicalSignal":"Neutral","fundamentalScore":"Weak","macroAlignment":"Neutral","date":"2026-06-12","priceAtPick":97.35,"timestamp":1781271177627}],"macro":{"spyPct":"0.22","qqqPct":"-0.25","vix":"0.0","tltPct":"-0.40","riskOn":false}}