{"date":"Wednesday, June 17, 2026","generated":"2026-06-17T13:29:17.283Z","batch":76,"picks":[{"sym":"ABM","name":"ABM Industries","sector":"Industrials","price":43.99,"change":-0.01,"pct":-0.0227,"pe":15.8508,"beta":0.7225289,"analystBuy":0,"analystSell":0,"rating":"BUY","confidence":72,"reason":"Low PE 15.9x, defensive beta 0.7, stable dividend yield attractive","target":47.5,"technicalSignal":"Neutral","fundamentalScore":"Strong","macroAlignment":"Favorable","date":"2026-06-17","priceAtPick":43.99,"timestamp":1781702950823},{"sym":"KELYA","name":"Kelly Services","sector":"Industrials","price":11.46,"change":-0.16,"pct":-1.3769,"pe":null,"beta":0.86704004,"analystBuy":0,"analystSell":0,"rating":"WATCH","confidence":45,"reason":"No PE ratio, limited analyst coverage, unclear valuation metrics","target":11.8,"technicalSignal":"Neutral","fundamentalScore":"Weak","macroAlignment":"Neutral","date":"2026-06-17","priceAtPick":11.46,"timestamp":1781702952056},{"sym":"MAN","name":"ManpowerGroup","sector":"Industrials","price":34.22,"change":0.87,"pct":2.6087,"pe":null,"beta":0.7268395,"analystBuy":0,"analystSell":0,"rating":"BUY","confidence":68,"reason":"Strong momentum +2.61%, low beta 0.73 suggests defensive stability","target":37.5,"technicalSignal":"Bullish","fundamentalScore":"Moderate","macroAlignment":"Neutral","date":"2026-06-17","priceAtPick":34.22,"timestamp":1781702953832},{"sym":"ASGN","name":"ASGN Inc","sector":"Industrials","price":21.02,"change":0.17,"pct":0.8153,"pe":6.9027,"beta":0.48732924,"analystBuy":0,"analystSell":0,"rating":"BUY","confidence":78,"reason":"Extremely low PE 6.9x with positive momentum and low volatility beta","target":23.5,"technicalSignal":"Bullish","fundamentalScore":"Strong","macroAlignment":"Favorable","date":"2026-06-17","priceAtPick":21.02,"timestamp":1781702956088},{"sym":"KFRC","name":"Kforce","sector":"Industrials","price":47.82,"change":0.15,"pct":0.3147,"pe":24.23,"beta":0.88967144,"analystBuy":0,"analystSell":0,"rating":"WATCH","confidence":62,"reason":"Moderate valuation with stable beta; lacks catalyst for upside","target":49.15,"technicalSignal":"Neutral","fundamentalScore":"Moderate","macroAlignment":"Neutral","date":"2026-06-17","priceAtPick":47.82,"timestamp":1781702957282}],"macro":{"spyPct":"-0.59","qqqPct":"-1.90","vix":"0.0","tltPct":"0.57","riskOn":false}}