{"date":"Wednesday, June 24, 2026","generated":"2026-06-24T14:17:50.303Z","batch":82,"picks":[{"sym":"MTDR","name":"Matador Resources","sector":"Energy","price":49.27,"change":-1.11,"pct":-2.2033,"pe":8.286,"beta":0.77806383,"analystBuy":0,"analystSell":0,"rating":"AVOID","confidence":76,"reason":"Revenue decline -10.1%, underperforming market -2.4%, short squeeze risk building","target":46.5,"technicalSignal":"Bearish","fundamentalScore":"Weak","macroAlignment":"Unfavorable","date":"2026-06-24","priceAtPick":49.27,"timestamp":1782310666148},{"sym":"PR","name":"Permian Resources","sector":"Energy","price":18.55,"change":-0.63,"pct":-3.2847,"pe":17.2933,"beta":0.49179295,"analystBuy":0,"analystSell":0,"rating":"AVOID","confidence":76,"reason":"Underperforming market -3.5% amid risk-off, negative revenue growth, analyst coverage gap","target":17.2,"technicalSignal":"Bearish","fundamentalScore":"Weak","macroAlignment":"Unfavorable","date":"2026-06-24","priceAtPick":18.55,"timestamp":1782310667346},{"sym":"CHRD","name":"Chord Energy","sector":"Energy","price":120.14,"change":-4.3,"pct":-3.4555,"pe":157.5805,"beta":0.3988428,"analystBuy":0,"analystSell":0,"rating":"AVOID","confidence":76,"reason":"Underperforming market -3.6%, PE 157.6x extreme, revenue declining, no analyst coverage","target":115.5,"technicalSignal":"Bearish","fundamentalScore":"Weak","macroAlignment":"Unfavorable","date":"2026-06-24","priceAtPick":120.14,"timestamp":1782310668950},{"sym":"CRGY","name":"Crescent Energy","sector":"Energy","price":10.15,"change":-0.37,"pct":-3.5171,"pe":26.1406,"beta":0.934885,"analystBuy":0,"analystSell":0,"rating":"AVOID","confidence":76,"reason":"Underperforming market -3.7%, surging short interest +11.58% MoM, no analyst coverage, no catalyst.","target":9.24,"technicalSignal":"Bearish","fundamentalScore":"Moderate","macroAlignment":"Unfavorable","date":"2026-06-24","priceAtPick":10.15,"timestamp":1782310670303}],"macro":{"spyPct":"0.19","qqqPct":"-0.13","vix":"0.0","tltPct":"1.29","riskOn":false}}