{"date":"Monday, June 29, 2026","generated":"2026-06-29T14:15:55.090Z","batch":49,"picks":[{"sym":"STLD","name":"Steel Dynamics","sector":"Materials","price":240.1,"change":-5.39,"pct":-2.1956,"pe":29.8608,"beta":1.5459908,"analystBuy":0,"analystSell":0,"rating":"AVOID","confidence":76,"reason":"Underperforming market -2.7%, elevated PE 29.9x, lower Q2 guidance, high beta 1.55 amplifies downside","target":218.5,"technicalSignal":"Bearish","fundamentalScore":"Deteriorating","macroAlignment":"Unfavorable","date":"2026-06-29","priceAtPick":240.1,"timestamp":1782742548989},{"sym":"ALB","name":"Albemarle","sector":"Materials","price":130.14,"change":-3.56,"pct":-2.6627,"pe":null,"beta":1.3870429,"analystBuy":0,"analystSell":0,"rating":"AVOID","confidence":76,"reason":"Underperforming market -3.2% in risk-off environment; weak margins 18.4%; lithium sector headwinds","target":122.5,"technicalSignal":"Bearish","fundamentalScore":"Weak","macroAlignment":"Unfavorable","date":"2026-06-29","priceAtPick":130.14,"timestamp":1782742550526},{"sym":"CF","name":"CF Industries","sector":"Materials","price":106.47,"change":0.77,"pct":0.7285,"pe":11.1606,"beta":0.41324085,"analystBuy":0,"analystSell":0,"rating":"WATCH","confidence":62,"reason":"No analyst coverage, risk-off environment conflicts with Materials strength","target":109.5,"technicalSignal":"Neutral","fundamentalScore":"Mixed","macroAlignment":"Conflicted","date":"2026-06-29","priceAtPick":106.47,"timestamp":1782742551791},{"sym":"MOS","name":"Mosaic","sector":"Materials","price":22.23,"change":-0.15,"pct":-0.6702,"pe":13.1559,"beta":0.8298788,"analystBuy":0,"analystSell":0,"rating":"BUY","confidence":76,"reason":"Rothschild initiation, attractive 13.2x PE, materials sector rotation potential","target":24.85,"technicalSignal":"Neutral","fundamentalScore":"Attractive","macroAlignment":"Favorable","date":"2026-06-29","priceAtPick":22.23,"timestamp":1782742553857},{"sym":"IFF","name":"Intl Flavors","sector":"Materials","price":75.8,"change":-0.55,"pct":-0.7204,"pe":22.8784,"beta":0.9425288,"analystBuy":0,"analystSell":0,"rating":"AVOID","confidence":76,"reason":"Revenue declining -5.6%, PE 22.9x unjustified by growth, sector outflow headwind","target":71.2,"technicalSignal":"Bearish","fundamentalScore":"Weak","macroAlignment":"Unfavorable","date":"2026-06-29","priceAtPick":75.8,"timestamp":1782742555089}],"macro":{"spyPct":"0.50","qqqPct":"0.07","vix":"0.0","tltPct":"0.01","riskOn":false}}