{"date":"Tuesday, June 23, 2026","generated":"2026-06-23T13:34:57.323Z","batch":56,"picks":[{"sym":"PPL","name":"PPL Corp","sector":"Utilities","price":35.39,"change":-0.2,"pct":-0.562,"pe":22.7521,"beta":0.6004486,"analystBuy":0,"analystSell":0,"rating":"AVOID","confidence":76,"reason":"Revenue collapse (-58.8%), sector rotating out, no analyst coverage, elevated valuation (PE 22.8x) for utility","target":32.8,"technicalSignal":"Bearish","fundamentalScore":"Weak","macroAlignment":"Unfavorable","date":"2026-06-23","priceAtPick":35.39,"timestamp":1782221691056},{"sym":"EIX","name":"Edison International","sector":"Utilities","price":72.03,"change":-0.17,"pct":-0.2355,"pe":5.8886,"beta":0.6762966,"analystBuy":0,"analystSell":0,"rating":"BUY","confidence":76,"reason":"Low PE 5.9x, high dividend yield spotlight, defensive beta suits risk-off environment","target":75.2,"technicalSignal":"Neutral","fundamentalScore":"Strong","macroAlignment":"Favorable","date":"2026-06-23","priceAtPick":72.03,"timestamp":1782221692193},{"sym":"PCG","name":"PG&E","sector":"Utilities","price":16.61,"change":-0.02,"pct":-0.1203,"pe":13.4961,"beta":0.29975072,"analystBuy":0,"analystSell":0,"rating":"AVOID","confidence":76,"reason":"Utilities underperforming in risk-off; negative analyst sentiment; reputational headwinds.","target":15.82,"technicalSignal":"Neutral","fundamentalScore":"Weak","macroAlignment":"Unfavorable","date":"2026-06-23","priceAtPick":16.61,"timestamp":1782221693467},{"sym":"AWK","name":"American Water Works","sector":"Utilities","price":126.32,"change":1.4,"pct":1.1207,"pe":21.9475,"beta":0.6023851,"analystBuy":0,"analystSell":0,"rating":"BUY","confidence":76,"reason":"Merger catalyst + sector rotation into utilities during risk-off. Low beta defensive play.","target":134.28,"technicalSignal":"Bullish","fundamentalScore":"Solid","macroAlignment":"Favorable","date":"2026-06-23","priceAtPick":126.32,"timestamp":1782221696151},{"sym":"WEC","name":"WEC Energy","sector":"Utilities","price":113.58,"change":0.54,"pct":0.4777,"pe":23.4405,"beta":0.46358475,"analystBuy":0,"analystSell":0,"rating":"WATCH","confidence":62,"reason":"Utilities sector rotating OUT amid risk-off; outperformance masks macro headwinds","target":115.5,"technicalSignal":"Neutral","fundamentalScore":"Fair","macroAlignment":"Unfavorable","date":"2026-06-23","priceAtPick":113.58,"timestamp":1782221697322}],"macro":{"spyPct":"-1.49","qqqPct":"-2.95","vix":"0.0","tltPct":"0.13","riskOn":false}}