{"date":"Monday, June 15, 2026","generated":"2026-06-15T13:38:14.281Z","batch":12,"picks":[{"sym":"BSX","name":"Boston Scientific","sector":"Health Care","price":47.57,"change":0.66,"pct":1.4069,"pe":24.0597,"beta":0.5620293,"analystBuy":0,"analystSell":0,"rating":"BUY","confidence":78,"reason":"Strong fundamentals, low beta defensive play, analyst support despite weakness","target":51.25,"technicalSignal":"Bullish","fundamentalScore":"Strong","macroAlignment":"Favorable","date":"2026-06-15","priceAtPick":47.57,"timestamp":1781530689827},{"sym":"CI","name":"Cigna","sector":"Health Care","price":293.34,"change":-4.66,"pct":-1.5638,"pe":13.2333,"beta":0.285172,"analystBuy":0,"analystSell":0,"rating":"BUY","confidence":72,"reason":"Low PE 13.2x, defensive beta, dividend champion with stable healthcare demand","target":315.5,"technicalSignal":"Neutral","fundamentalScore":"Strong","macroAlignment":"Favorable","date":"2026-06-15","priceAtPick":293.34,"timestamp":1781530690951},{"sym":"ADI","name":"Analog Devices","sector":"Technology","price":432.38,"change":14.59,"pct":3.4922,"pe":89.7527,"beta":1.1954709,"analystBuy":0,"analystSell":0,"rating":"WATCH","confidence":58,"reason":"High valuation at 89.8x PE offsets positive technicals and dividend strength","target":445,"technicalSignal":"Bullish","fundamentalScore":"Moderate","macroAlignment":"Neutral","date":"2026-06-15","priceAtPick":432.38,"timestamp":1781530692929},{"sym":"SO","name":"Southern Company","sector":"Utilities","price":92.98,"change":-1.02,"pct":-1.0851,"pe":24.4106,"beta":0.33028495,"analystBuy":0,"analystSell":0,"rating":"BUY","confidence":72,"reason":"Low beta defensive utility, strong dividend, stable cash flows support valuation","target":98.5,"technicalSignal":"Neutral","fundamentalScore":"Strong","macroAlignment":"Favorable","date":"2026-06-15","priceAtPick":92.98,"timestamp":1781530694280}],"macro":{"spyPct":"1.56","qqqPct":"2.58","vix":"0.0","tltPct":"0.26","riskOn":false}}