{"date":"Tuesday, June 23, 2026","generated":"2026-06-23T14:07:25.514Z","batch":68,"picks":[{"sym":"PODD","name":"Insulet","sector":"Health Care","price":144.77,"change":5.8,"pct":4.1736,"pe":40.858,"beta":1.1296133,"analystBuy":0,"analystSell":0,"rating":"BUY","confidence":76,"reason":"Next-gen automation catalyst, strong growth (31.9% rev), outperforming +5.0% vs market headwinds","target":158.5,"technicalSignal":"Bullish","fundamentalScore":"Strong","macroAlignment":"Favorable","date":"2026-06-23","priceAtPick":144.77,"timestamp":1782223636996},{"sym":"TNDM","name":"Tandem Diabetes","sector":"Health Care","price":14.13,"change":-0.21,"pct":-1.4644,"pe":null,"beta":1.5601393,"analystBuy":0,"analystSell":0,"rating":"AVOID","confidence":76,"reason":"Elevated short interest building, no analyst coverage, sector rotating out","target":13.2,"technicalSignal":"Bearish","fundamentalScore":"Weak","macroAlignment":"Unfavorable","date":"2026-06-23","priceAtPick":14.13,"timestamp":1782223638048},{"sym":"BDX","name":"Becton Dickinson","sector":"Health Care","price":143.42,"change":2.71,"pct":1.9259,"pe":23.4291,"beta":0.22241288,"analystBuy":0,"analystSell":0,"rating":"BUY","confidence":76,"reason":"Vizient contract catalyst, outperforming sector rotation, defensive beta supports upside","target":148.5,"technicalSignal":"Bullish","fundamentalScore":"Strong","macroAlignment":"Favorable","date":"2026-06-23","priceAtPick":143.42,"timestamp":1782223640244},{"sym":"BAX","name":"Baxter","sector":"Health Care","price":19.85,"change":0.19,"pct":0.9664,"pe":null,"beta":0.6246366,"analystBuy":0,"analystSell":0,"rating":"WATCH","confidence":62,"reason":"Outperforming amid sector rotation out, but revenue declining, no analyst coverage","target":20.5,"technicalSignal":"Bullish","fundamentalScore":"Weak","macroAlignment":"Neutral","date":"2026-06-23","priceAtPick":19.85,"timestamp":1782223645514}],"macro":{"spyPct":"-0.87","qqqPct":"-2.20","vix":"0.0","tltPct":"0.31","riskOn":false}}