{"date":"Monday, June 29, 2026","generated":"2026-06-29T14:13:54.457Z","batch":67,"picks":[{"sym":"BIIB","name":"Biogen","sector":"Health Care","price":215.54,"change":-0.49,"pct":-0.2268,"pe":24.6686,"beta":0.13632354,"analystBuy":0,"analystSell":0,"rating":"AVOID","confidence":76,"reason":"Pipeline trimming signals R&D struggle; low revenue growth amid sector rotation out","target":205.21,"technicalSignal":"Neutral","fundamentalScore":"Weak","macroAlignment":"Unfavorable","date":"2026-06-29","priceAtPick":215.54,"timestamp":1782742431488},{"sym":"ALNY","name":"Alnylam","sector":"Health Care","price":293.89,"change":2.52,"pct":0.8649,"pe":123.9902,"beta":0.2660804,"analystBuy":0,"analystSell":0,"rating":"WATCH","confidence":62,"reason":"No analyst coverage, extreme PE valuation, sector headwinds offset strong growth metrics","target":305,"technicalSignal":"Neutral","fundamentalScore":"Mixed","macroAlignment":"Unfavorable","date":"2026-06-29","priceAtPick":293.89,"timestamp":1782742432963},{"sym":"DXCM","name":"Dexcom","sector":"Health Care","price":70.62,"change":0.48,"pct":0.6843,"pe":32.3629,"beta":1.4141008,"analystBuy":0,"analystSell":0,"rating":"WATCH","confidence":62,"reason":"Health Care sector rotating out; elevated valuation (32.4x PE) vs mixed technicals","target":72.5,"technicalSignal":"Neutral","fundamentalScore":"Mixed","macroAlignment":"Unfavorable","date":"2026-06-29","priceAtPick":70.62,"timestamp":1782742434456}],"macro":{"spyPct":"0.67","qqqPct":"0.36","vix":"0.0","tltPct":"0.11","riskOn":false}}